pydfuutil/__init__.py
pydfuutil/__main__.py
pydfuutil/dfu.py
pydfuutil/dfu_file.py
pydfuutil/dfu_load.py
pydfuutil/dfuse.py
pydfuutil/dfuse_mem.py
pydfuutil/exceptions.py
pydfuutil/lmdfu.py
pydfuutil/logger.py
pydfuutil/portable.py
pydfuutil/progress.py
pydfuutil/quirks.py
pydfuutil/suffix.py
pydfuutil/usb_dfu.py
pydfuutil-0.0.5.dist-info/LICENSE
pydfuutil-0.0.5.dist-info/METADATA
pydfuutil-0.0.5.dist-info/WHEEL
pydfuutil-0.0.5.dist-info/entry_points.txt
pydfuutil-0.0.5.dist-info/top_level.txt
pydfuutil-0.0.5.dist-info/RECORD
