Metadata-Version: 2.1
Name: pydfuutil
Version: 0.0.5
Summary: PyDfuUtil - Pure python fork of dfu-util wrappers to libusb
Author-email: o-murphy <thehelixpg@gmail.com>
License: GNU LESSER GENERAL PUBLIC LICENSE
Project-URL: Homepage, https://github.com/o-murphy/pydfuutil
Project-URL: Bug Reports, https://github.com/o-murphy/pydfuutil/issues
Project-URL: Source, https://github.com/o-murphy/pydfuutil
Keywords: dfu_util,dfu-util,pydfu,libusb,python,python3
Classifier: Intended Audience :: Developers
Classifier: Natural Language :: English
Classifier: Programming Language :: Python
Classifier: Topic :: Software Development :: Libraries :: Python Modules
Classifier: Programming Language :: Python :: 3
Classifier: Programming Language :: Python :: 3 :: Only
Classifier: Programming Language :: Python :: 3.9
Classifier: Programming Language :: Python :: 3.10
Classifier: Programming Language :: Python :: 3.11
Classifier: Programming Language :: Python :: 3.12
Classifier: Operating System :: OS Independent
Classifier: Programming Language :: Python :: Implementation :: CPython
Requires-Python: >=3.9
License-File: LICENSE
Requires-Dist: pyusb
Requires-Dist: libusb-package
Requires-Dist: construct
Provides-Extra: build
Requires-Dist: build ; extra == 'build'
Provides-Extra: rich
Requires-Dist: rich ; extra == 'rich'
Provides-Extra: test
Requires-Dist: pytest ; extra == 'test'
Requires-Dist: pylint ; extra == 'test'
